hive_mind_mcp-1.0.14.dist-info/licenses/LICENSE
src/__init__.py
src/cli.py
src/config.py
src/dashboard.py
src/dashboard_utils.py
src/logger.py
src/persistence.py
src/personas.py
src/schemas.py
src/security.py
src/server.py
src/tools.py
src/models/model_registry.py
src/pipelines/engine.py
src/pipelines/state_manager.py
src/planner/complexity_analyzer.py
src/planner/dynamic_planner.py
src/planner/intent_classifier.py
src/providers/anthropic.py
src/providers/base.py
src/providers/deepseek.py
src/providers/gemini.py
src/providers/groq.py
src/providers/mistral.py
src/providers/openai.py
src/providers/openai_compatible.py
src/providers/openrouter.py
src/providers/tool_aware_provider.py
src/ui/__init__.py
src/ui/presentation.py
src/utils/sandbox_utils.py
src/watchdog/__init__.py
src/watchdog/engine.py
src/watchdog/ingest.py
hive_mind_mcp-1.0.14.dist-info/METADATA
hive_mind_mcp-1.0.14.dist-info/WHEEL
hive_mind_mcp-1.0.14.dist-info/entry_points.txt
hive_mind_mcp-1.0.14.dist-info/top_level.txt
hive_mind_mcp-1.0.14.dist-info/RECORD
