Metadata-Version: 2.4
Name: hive-mind-mcp
Version: 1.0.14
Summary: MCP Server for orchestrating LLM interactions
Author-email: Hive Mind Team <hello@example.com>
License: Apache-2.0
Project-URL: Homepage, https://github.com/franciscojunqueira/hive-mind-mcp
Project-URL: Repository, https://github.com/franciscojunqueira/hive-mind-mcp
Project-URL: Issues, https://github.com/franciscojunqueira/hive-mind-mcp/issues
Keywords: mcp,llm,orchestrator,agent,ai
Classifier: Development Status :: 4 - Beta
Classifier: Intended Audience :: Developers
Classifier: License :: OSI Approved :: Apache Software License
Classifier: Programming Language :: Python :: 3
Classifier: Programming Language :: Python :: 3.10
Classifier: Programming Language :: Python :: 3.11
Classifier: Topic :: Scientific/Engineering :: Artificial Intelligence
Requires-Python: >=3.10
License-File: LICENSE
Requires-Dist: mcp[cli]>=1.0.0
Requires-Dist: openai>=1.0.0
Requires-Dist: anthropic>=0.3.0
Requires-Dist: python-dotenv>=1.0.0
Requires-Dist: tenacity>=8.0.0
Requires-Dist: pydantic>=2.0.0
Requires-Dist: pydantic-settings>=2.0.0
Requires-Dist: structlog>=24.0.0
Requires-Dist: google-generativeai>=0.5.0
Requires-Dist: streamlit>=1.30.0
Requires-Dist: pandas>=2.0.0
Requires-Dist: plotly>=5.0.0
Requires-Dist: PyYAML>=6.0
Requires-Dist: docker>=7.0.0
Provides-Extra: dev
Requires-Dist: pytest>=7.0.0; extra == "dev"
Requires-Dist: pytest-asyncio>=0.21.0; extra == "dev"
Requires-Dist: pytest-cov>=4.0.0; extra == "dev"
Requires-Dist: pytest-mock>=3.10.0; extra == "dev"
Requires-Dist: pytest-benchmark>=4.0.0; extra == "dev"
Requires-Dist: build>=1.0.0; extra == "dev"
Requires-Dist: twine>=4.0.0; extra == "dev"
Dynamic: license-file
